sailreval/__init__.py
sailreval/loggercfg.py
sailreval/analysis/__init__.py
sailreval/analysis/counting.py
sailreval/analysis/measure.py
sailreval/analysis/visualization.py
sailreval/decompilers/__init__.py
sailreval/decompilers/angr_dec.py
sailreval/decompilers/ghidra_dec.py
sailreval/decompilers/ida_dec.py
sailreval/metrics/__init__.py
sailreval/metrics/cyclomatic_complexity.py
sailreval/metrics/duplication.py
sailreval/metrics/ged_to_source.py
sailreval/metrics/graph_utils.py
sailreval/metrics/logic_continuity.py
sailreval/metrics/nesting_count.py
sailreval/metrics/post_metrics.py
sailreval/metrics/total_bools.py
sailreval/metrics/total_gotos.py
sailreval/metrics/total_loc.py
sailreval/metrics/total_paths.py
sailreval/utils/__init__.py
sailreval/utils/binary_debug_info.py
sailreval/utils/compile.py
sailreval/utils/results.py
sailreval/utils/sailr_target.py
sailreval-1.6.0.dist-info/LICENSE
sailreval-1.6.0.dist-info/METADATA
sailreval-1.6.0.dist-info/WHEEL
sailreval-1.6.0.dist-info/top_level.txt
sailreval-1.6.0.dist-info/RECORD
