Metadata-Version: 2.1
Name: sailreval
Version: 1.6.0
Summary: The SAILR Evaluation Pipeline
Home-page: https://github.com/mahaloz/sailr-eval
License: BSD 2 Clause
Classifier: License :: OSI Approved :: BSD License
Classifier: Programming Language :: Python :: 3
Classifier: Programming Language :: Python :: 3.8
Requires-Python: >=3.8
License-File: LICENSE
Requires-Dist: networkx
Requires-Dist: toml
Requires-Dist: tqdm
Requires-Dist: pyelftools
Requires-Dist: cfgutils >=1.10.2
Requires-Dist: pyjoern ==1.2.18.6
Provides-Extra: viz
Requires-Dist: matplotlib ; extra == 'viz'
Requires-Dist: numpy ; extra == 'viz'
Requires-Dist: pandas ; extra == 'viz'
Requires-Dist: seaborn ; extra == 'viz'
